alldatetime/__init__.py
alldatetime/alldatetime.py
alldatetime/fuzzydatetime.py
alldatetime-0.1.7.dist-info/METADATA
alldatetime-0.1.7.dist-info/WHEEL
alldatetime-0.1.7.dist-info/licenses/LICENSE
alldatetime-0.1.7.dist-info/RECORD
