Metadata-Version: 2.4
Name: alldatetime
Version: 0.1.7
Summary: This is a lightweight Python library for representing time and dates, with no restrictions on the year range. (Unlike the datetime library in CPython, which has a year range from 1 to 9999.) It also supports fuzzy dates, allowing for representation of uncertain times (i.e., you can specify only the year, month, or day). For example, it can represent dates like 1912, or March 1912, etc.
Project-URL: Homepage, https://github.com/timewalker08/alldatetime
Project-URL: Bug Tracker, https://github.com/timewalker08/alldatetime/issues
Author-email: Simin Lin <timewalker08@outlook.com>
License-File: LICENSE
Classifier: License :: OSI Approved :: MIT License
Classifier: Operating System :: OS Independent
Classifier: Programming Language :: Python :: 3
Requires-Python: >=3.7
